ggv/utils/__init__.py
ggv/utils/config.py
ggv.utils-0.1.1.data/data/my_data/data_file
ggv.utils-0.1.1.dist-info/DESCRIPTION.rst
ggv.utils-0.1.1.dist-info/LICENSE.txt
ggv.utils-0.1.1.dist-info/METADATA
ggv.utils-0.1.1.dist-info/RECORD
ggv.utils-0.1.1.dist-info/WHEEL
ggv.utils-0.1.1.dist-info/metadata.json
ggv.utils-0.1.1.dist-info/top_level.txt
